funkcije.py
dz4vz-1.0.2.dist-info/METADATA
dz4vz-1.0.2.dist-info/RECORD
dz4vz-1.0.2.dist-info/WHEEL
dz4vz-1.0.2.dist-info/top_level.txt
