Metadata-Version: 2.1
Name: dz4vz
Version: 1.0.2
Summary: Domaci zadatak 4 - V. Zivkovic
Home-page: UNKNOWN
Author: V. Zivkovic
Author-email: vzivkovic510@gmail.com
License: UNKNOWN
Keywords: domaci zadatak broj 4
Platform: UNKNOWN
Classifier: Development Status :: 5 - Production/Stable
Classifier: Intended Audience :: Education
Classifier: Topic :: Education :: Testing
Classifier: License :: OSI Approved :: MIT License
Classifier: Programming Language :: Python :: 2
Classifier: Programming Language :: Python :: 2.7
Classifier: Programming Language :: Python :: 3
Classifier: Programming Language :: Python :: 3.4
Classifier: Programming Language :: Python :: 3.5
Classifier: Programming Language :: Python :: 3.6
Classifier: Programming Language :: Python :: 3.7
